LICENSE
MANIFEST.in
README.md
requirements.txt
setup.py
tests/__init__.py
tests/trainer_test.py
tests/model/__init__.py
tests/model/catboost_kwargs_test.py
wavetrainer/__init__.py
wavetrainer/create.py
wavetrainer/crps.py
wavetrainer/exceptions.py
wavetrainer/fit.py
wavetrainer/model_type.py
wavetrainer/params.py
wavetrainer/stratified_brier_score_loss.py
wavetrainer/threshold_callback.py
wavetrainer/trainer.py
wavetrainer.egg-info/PKG-INFO
wavetrainer.egg-info/SOURCES.txt
wavetrainer.egg-info/dependency_links.txt
wavetrainer.egg-info/not-zip-safe
wavetrainer.egg-info/requires.txt
wavetrainer.egg-info/top_level.txt
wavetrainer/calibrator/__init__.py
wavetrainer/calibrator/calibrator.py
wavetrainer/calibrator/calibrator_router.py
wavetrainer/calibrator/conformal_quantile_calibration.py
wavetrainer/calibrator/vennabers_calibrator.py
wavetrainer/model/__init__.py
wavetrainer/model/model.py
wavetrainer/model/model_router.py
wavetrainer/model/catboost/__init__.py
wavetrainer/model/catboost/catboost_classifier_wrap.py
wavetrainer/model/catboost/catboost_kwargs.py
wavetrainer/model/catboost/catboost_model.py
wavetrainer/model/catboost/catboost_regressor_wrap.py
wavetrainer/model/lightgbm/__init__.py
wavetrainer/model/lightgbm/lightgbm_model.py
wavetrainer/model/tabpfn/__init__.py
wavetrainer/model/tabpfn/tabpfn_model.py
wavetrainer/model/xgboost/__init__.py
wavetrainer/model/xgboost/early_stopper.py
wavetrainer/model/xgboost/xgboost_logger.py
wavetrainer/model/xgboost/xgboost_model.py
wavetrainer/normaliser/__init__.py
wavetrainer/normaliser/combined_normaliser.py
wavetrainer/normaliser/normaliser.py
wavetrainer/normaliser/powertransformer_normaliser.py
wavetrainer/reducer/__init__.py
wavetrainer/reducer/base_selector_reducer.py
wavetrainer/reducer/combined_reducer.py
wavetrainer/reducer/constant_reducer.py
wavetrainer/reducer/correlation_reducer.py
wavetrainer/reducer/duplicate_reducer.py
wavetrainer/reducer/non_categorical_numeric_columns.py
wavetrainer/reducer/nonnumeric_reducer.py
wavetrainer/reducer/pca_reducer.py
wavetrainer/reducer/reducer.py
wavetrainer/reducer/select_by_single_feature_performance_reducer.py
wavetrainer/reducer/smart_correlation_reducer.py
