Metadata-Version: 2.1
Name: wavetrainer
Version: 0.3.9
Summary: A library for automatically finding the optimal model within feature and hyperparameter space.
Home-page: https://github.com/8W9aG/wavetrainer
Author: Will Sackfield
Author-email: will.sackfield@gmail.com
License: MIT
Keywords: machine-learning,ML,hyperparameter,features
Classifier: License :: OSI Approved :: MIT License
Classifier: Programming Language :: Python :: 3
License-File: LICENSE
Requires-Dist: pandas>=2.2.3
Requires-Dist: optuna>=4.2.1
Requires-Dist: scikit-learn>=1.5.2
Requires-Dist: feature-engine>=1.8.3
Requires-Dist: tqdm>=4.67.1
Requires-Dist: numpy>=1.26.4
Requires-Dist: scipy>=1.15.2
Requires-Dist: catboost>=1.2.7
Requires-Dist: venn-abers>=1.4.6
Requires-Dist: pytz>=2025.1
Requires-Dist: torch>=2.6.0
Requires-Dist: tabpfn>=2.0.6
Requires-Dist: pytest-is-running>=1.5.1
Requires-Dist: xgboost>=3.0.0
Requires-Dist: jax>=0.6.1
Requires-Dist: tabpfn_extensions>=0.0.4
Requires-Dist: hyperopt>=0.2.7
Requires-Dist: pycaleva>=0.8.2
Requires-Dist: lightgbm>=4.6.0
Requires-Dist: kaleido>=0.2.1
Requires-Dist: memory-profiler>=0.61.0
Requires-Dist: matplotlib>=3.10.1
Requires-Dist: pyarrow>=19.0.1
Requires-Dist: scores>=2.3.0
Requires-Dist: xarray>=2025.11.0
